diff_getter/__init__.py
diff_getter/__main__.py
diff_getter/context_diff_getter.py
diff_getter/server.py
diff_getter/unified_diff_getter.py
diff_getter-0.1.18.dist-info/METADATA
diff_getter-0.1.18.dist-info/WHEEL
diff_getter-0.1.18.dist-info/entry_points.txt
diff_getter-0.1.18.dist-info/licenses/LICENSE
diff_getter-0.1.18.dist-info/RECORD
