Metadata-Version: 2.4
Name: diff-getter
Version: 0.1.18
Summary: A tool to get diffs between text strings
Project-URL: Homepage, https://github.com/tatn/diff-getter-python
Project-URL: Repository, https://github.com/tatn/diff-getter-python
Author: tatn
License-Expression: MIT
License-File: LICENSE
Classifier: Development Status :: 3 - Alpha
Classifier: Intended Audience :: Developers
Classifier: License :: OSI Approved :: MIT License
Classifier: Programming Language :: Python :: 3
Classifier: Programming Language :: Python :: 3.10
Requires-Python: >=3.10
